[{"id":2141,"title":"Welcome to the Gutenberg Editor","link":"http:\/\/wordsite.local\/welcome-to-the-gutenberg-editor\/","post_type":"post","updated":"2025-12-04T07:38:40+00:00","images":8,"images_data":[{"link":"https:\/\/cldup.com\/Fz-ASbo2s3.jpg","updated":"2025-12-04T07:38:40+00:00"},{"link":"https:\/\/cldup.com\/cXyG__fTLN.jpg","updated":"2025-12-04T07:38:40+00:00"},{"link":"https:\/\/cldup.com\/n0g6ME5VKC.jpg","updated":"2025-12-04T07:38:40+00:00"},{"link":"https:\/\/cldup.com\/ZjESfxPI3R.jpg","updated":"2025-12-04T07:38:40+00:00"},{"link":"https:\/\/cldup.com\/EKNF8xD2UM.jpg","updated":"2025-12-04T07:38:40+00:00"},{"link":"https:\/\/cldup.com\/8lhI-gKnI2.jpg","updated":"2025-12-04T07:38:40+00:00"},{"link":"https:\/\/cldup.com\/_rSwtEeDGD.jpg","updated":"2025-12-04T07:38:40+00:00"},{"link":"https:\/\/cldup.com\/L-cC3qX2DN.jpg","updated":"2025-12-04T07:38:40+00:00"}]},{"id":1,"title":"Hello world!","link":"http:\/\/wordsite.local\/hello-world\/","post_type":"post","updated":"2025-12-04T05:04:31+00:00","images":0,"images_data":[]}]